diGraph/__init__.py
diGraph/diGraph.py
diGraph-0.1.4.dist-info/LICENSE
diGraph-0.1.4.dist-info/METADATA
diGraph-0.1.4.dist-info/WHEEL
diGraph-0.1.4.dist-info/top_level.txt
diGraph-0.1.4.dist-info/RECORD
