Metadata-Version: 2.1
Name: diGraph
Version: 0.1.4
Summary: For plotting DiGraphs
Home-page: https://github.com/francisp336/diGraph
Author: Peter Francis
Author-email: franpe02@gettysburg.edu
License: UNKNOWN
Keywords: DiGraph
Platform: UNKNOWN
Requires-Python: >=3.0.0
